coreason_optimizer/__init__.py
coreason_optimizer/core/__init__.py
coreason_optimizer/core/budget.py
coreason_optimizer/core/client.py
coreason_optimizer/core/config.py
coreason_optimizer/core/formatter.py
coreason_optimizer/core/interfaces.py
coreason_optimizer/core/metrics.py
coreason_optimizer/core/models.py
coreason_optimizer/data/loader.py
coreason_optimizer/main.py
coreason_optimizer/server.py
coreason_optimizer/server_schemas.py
coreason_optimizer/strategies/bootstrap.py
coreason_optimizer/strategies/mipro.py
coreason_optimizer/strategies/mutator.py
coreason_optimizer/strategies/selector.py
coreason_optimizer/utils/__init__.py
coreason_optimizer/utils/exceptions.py
coreason_optimizer/utils/import_utils.py
coreason_optimizer/utils/logger.py
coreason_optimizer-0.3.0.dist-info/METADATA
coreason_optimizer-0.3.0.dist-info/WHEEL
coreason_optimizer-0.3.0.dist-info/entry_points.txt
coreason_optimizer-0.3.0.dist-info/licenses/LICENSE
coreason_optimizer-0.3.0.dist-info/licenses/NOTICE
coreason_optimizer-0.3.0.dist-info/RECORD
