Metadata-Version: 2.4
Name: coreason_optimizer
Version: 0.3.0
Summary: coreason-optimizer
License: Prosperity-3.0
License-File: LICENSE
License-File: NOTICE
Author: Gowtham A Rao
Author-email: gowtham.rao@coreason.ai
Requires-Python: >=3.12,<3.15
Classifier: License :: Other/Proprietary License
Classifier: Programming Language :: Python :: 3
Classifier: Programming Language :: Python :: 3.12
Classifier: Programming Language :: Python :: 3.13
Classifier: Programming Language :: Python :: 3.14
Requires-Dist: aiofiles
Requires-Dist: anyio (>=4.12.1,<5.0.0)
Requires-Dist: click (>=8.1.7,<9.0.0)
Requires-Dist: coreason-identity (>=0.4.1,<0.5.0)
Requires-Dist: fastapi (>=0.128.0,<0.129.0)
Requires-Dist: httpx (>=0.28.1,<0.29.0)
Requires-Dist: jinja2 (>=3.1.4,<4.0.0)
Requires-Dist: loguru (>=0.7.2,<0.8.0)
Requires-Dist: numpy (>=2.4,<3.0)
Requires-Dist: openai (>=2.16,<3.0)
Requires-Dist: pydantic (>=2.10,<3.0)
Requires-Dist: scikit-learn (>=1.8,<2.0)
Requires-Dist: types-aiofiles
Requires-Dist: uvicorn (>=0.40.0,<0.41.0)
